LICENSE
MANIFEST
MANIFEST.in
README.rst
requirements.txt
setup.cfg
setup.py
news_api/__init__.py
news_api/news.py
news_api/news_config.py
news_api.egg-info/PKG-INFO
news_api.egg-info/SOURCES.txt
news_api.egg-info/dependency_links.txt
news_api.egg-info/not-zip-safe
news_api.egg-info/requires.txt
news_api.egg-info/top_level.txt