Metadata-Version: 1.1
Name: news_api
Version: 1.0.2
Summary: API of news in China.
Home-page: https://github.com/shinalone/news_api
Author: UlionTse
Author-email: shinalone@outlook.com
License: MIT
Keywords: news_api,News,news,NewsApi,newsAPI
Platform: UNKNOWN
Classifier: Development Status :: 4 - Beta
Classifier: Environment :: Web Environment
Classifier: Intended Audience :: Developers
Classifier: License :: OSI Approved :: MIT License
Classifier: Programming Language :: Python :: 3.4
Classifier: Programming Language :: Python :: 3.5
Classifier: Programming Language :: Python :: 3.6
